neuralib/registration/__init__.py
neuralib/registration/coordinates.py
neuralib/spikes/__init__.py
neuralib/spikes/cascade.py
neuralib/spikes/oasis.py
neuralib/widefield/__init__.py
neuralib/widefield/align.py
neuralib/widefield/fft.py
neuralib/widefield/fft_view.py
neuralib/widefield/main_app.py
neuralib/widefield/plot.py
neuralib/widefield/svd.py
neuralib_imaging-0.7.0.dist-info/licenses/LICENSE
neuralib_imaging-0.7.0.dist-info/METADATA
neuralib_imaging-0.7.0.dist-info/WHEEL
neuralib_imaging-0.7.0.dist-info/top_level.txt
neuralib_imaging-0.7.0.dist-info/RECORD
